cvsx2mvsx/__init__.py
cvsx2mvsx/cli.py
cvsx2mvsx/etl/__init__.py
cvsx2mvsx/etl/extract/__init__.py
cvsx2mvsx/etl/extract/cvsx.py
cvsx2mvsx/etl/extract/internal.py
cvsx2mvsx/etl/extract/parsers/__init__.py
cvsx2mvsx/etl/extract/parsers/common.py
cvsx2mvsx/etl/extract/parsers/geometric.py
cvsx2mvsx/etl/extract/parsers/interface.py
cvsx2mvsx/etl/extract/parsers/lattice.py
cvsx2mvsx/etl/extract/parsers/mesh.py
cvsx2mvsx/etl/extract/parsers/volume.py
cvsx2mvsx/etl/load/__init__.py
cvsx2mvsx/etl/load/internal.py
cvsx2mvsx/etl/load/mvstory.py
cvsx2mvsx/etl/load/mvsx.py
cvsx2mvsx/etl/load/encoders/__init__.py
cvsx2mvsx/etl/load/encoders/encoders.py
cvsx2mvsx/etl/load/encoders/lattice.py
cvsx2mvsx/etl/load/encoders/volume_data_3d.py
cvsx2mvsx/etl/load/encoders/volume_data_3d_info.py
cvsx2mvsx/etl/load/encoders/volume_data_time_and_channel_info.py
cvsx2mvsx/etl/pipelines/config.py
cvsx2mvsx/etl/pipelines/context.py
cvsx2mvsx/etl/pipelines/pipeline.py
cvsx2mvsx/etl/pipelines/pipeline_steps.py
cvsx2mvsx/etl/transform/__init__.py
cvsx2mvsx/etl/transform/common.py
cvsx2mvsx/etl/transform/geometric.py
cvsx2mvsx/etl/transform/internal.py
cvsx2mvsx/etl/transform/lattice.py
cvsx2mvsx/etl/transform/mesh.py
cvsx2mvsx/etl/transform/mvstory.py
cvsx2mvsx/etl/transform/mvsx.py
cvsx2mvsx/etl/transform/volume.py
cvsx2mvsx/models/__init__.py
cvsx2mvsx/models/cvsx/__init__.py
cvsx2mvsx/models/cvsx/annotations.py
cvsx2mvsx/models/cvsx/common.py
cvsx2mvsx/models/cvsx/entry.py
cvsx2mvsx/models/cvsx/geometric.py
cvsx2mvsx/models/cvsx/index.py
cvsx2mvsx/models/cvsx/lattice.py
cvsx2mvsx/models/cvsx/mesh.py
cvsx2mvsx/models/cvsx/metadata.py
cvsx2mvsx/models/cvsx/proxy.py
cvsx2mvsx/models/cvsx/query.py
cvsx2mvsx/models/cvsx/volume.py
cvsx2mvsx/models/internal/__init__.py
cvsx2mvsx/models/internal/entry.py
cvsx2mvsx/models/internal/segment.py
cvsx2mvsx/models/internal/segmentation.py
cvsx2mvsx/models/internal/timeframe.py
cvsx2mvsx/models/internal/types.py
cvsx2mvsx/models/internal/volume.py
cvsx2mvsx-1.0.0.dist-info/METADATA
cvsx2mvsx-1.0.0.dist-info/WHEEL
cvsx2mvsx-1.0.0.dist-info/entry_points.txt
cvsx2mvsx-1.0.0.dist-info/licenses/LICENSE
cvsx2mvsx-1.0.0.dist-info/RECORD
