Metadata-Version: 2.4
Name: cvsx2mvsx
Version: 1.0.0
Summary: Library for converting the CVSX file format into the MVSX file format
Project-URL: Homepage, https://github.com/dominikandrewtichy/cvsx2mvsx
Project-URL: Bug Tracker, https://github.com/dominikandrewtichy/cvsx2mvsx/issues
Author-email: Dominik Andrew Tichy <tichydominik451@gmail.com>
License: Apache-2.0
License-File: LICENSE
Classifier: License :: OSI Approved :: Apache Software License
Classifier: Operating System :: OS Independent
Classifier: Programming Language :: Python :: 3
Classifier: Topic :: Scientific/Engineering :: Bio-Informatics
Requires-Python: >=3.12
Requires-Dist: ciftools>=0.2.1
Requires-Dist: numpy>=2.3.5
Requires-Dist: pydantic>=2.12.3
Requires-Dist: requests>=2.32.5
Requires-Dist: scikit-image>=0.25.2
